__init__.py
fitting_toolkit.py
fitting_toolkit/__init__.py
fitting_toolkit/fit.py
fitting_toolkit/fitting_toolkit.py
fitting_toolkit/utils.py
fitting_toolkit-1.1.0.dist-info/LICENSE
fitting_toolkit-1.1.0.dist-info/METADATA
fitting_toolkit-1.1.0.dist-info/WHEEL
fitting_toolkit-1.1.0.dist-info/top_level.txt
fitting_toolkit-1.1.0.dist-info/RECORD
