Metadata-Version: 2.1
Name: fitting_toolkit
Version: 1.1.0
Summary: Easy and Flexible Curve Fitting
Home-page: https://github.com/davidkowalk/fitting_toolkit/
License: MIT
Project-URL: Documentation, https://github.com/davidkowalk/fitting_toolkit/blob/Stable/docs/manual.md
Project-URL: Source, https://github.com/davidkowalk/fitting_toolkit/
Project-URL: Tracker, https://github.com/davidkowalk/fitting_toolkit/issues
Classifier: Programming Language :: Python
Classifier: Programming Language :: Python :: 3
Classifier: Natural Language :: English
License-File: LICENSE
Requires-Dist: contourpy==1.3.1
Requires-Dist: cycler==0.12.1
Requires-Dist: fonttools==4.55.0
Requires-Dist: kiwisolver==1.4.7
Requires-Dist: matplotlib==3.9.2
Requires-Dist: numpy==2.1.3
Requires-Dist: packaging==24.2
Requires-Dist: pillow==11.0.0
Requires-Dist: pyparsing==3.2.0
Requires-Dist: python-dateutil==2.9.0.post0
Requires-Dist: scipy==1.14.1
Requires-Dist: six==1.16.0
